telenvi/GeoIm.py
telenvi/__init__.py
telenvi/associations.py
telenvi/raster_tools.py
telenvi/vector_tools.py
telenvi-5.0.9.dist-info/LICENSE
telenvi-5.0.9.dist-info/METADATA
telenvi-5.0.9.dist-info/WHEEL
telenvi-5.0.9.dist-info/top_level.txt
telenvi-5.0.9.dist-info/RECORD
