Metadata-Version: 2.1
Name: telenvi
Version: 5.0.9
Summary: Some remote sensing tricks from telenvi master students
Home-page: https://github.com/pyzak117/telenvi
Author: Thibaut Duvanel, Julien Pellen
Author-email: thibaut.duvanel@univ-savoie.fr
Project-URL: Bug Tracker, https://github.com/pyzak117/telenvi/issues
Classifier: Programming Language :: Python :: 3
Classifier: License :: OSI Approved :: MIT License
Classifier: Operating System :: OS Independent
Requires-Python: >=3.6
License-File: LICENSE
